Workbook

Sheet Diseno de Caudal
A1: DISENO DE CAUDAL - ACUEDUCTO DE TADO (Resolucion 0330 de 2017 - RAS)
A3: Parametro | B3: Valor | C3: Unidad / Fuente
A4: Poblacion municipio (CNPV 2018, DANE) | B4: 17000 | C4: hab
A5: Fraccion urbana (estimada) | B5: 0.6 | C5: %
A6: Poblacion urbana 2018 | B6: =B4*B5 | C6: hab
A7: Anio base | B7: 2024 | C7: anio
A8: Tasa de crecimiento anual | B8: 0.012 | C8: %
A9: Periodo de diseno | B9: 25 | C9: anios
A10: Poblacion urbana base | B10: =B6*(1+B8)^(B7-2018) | C10: hab
A11: Poblacion de diseno | B11: =B10*(1+B8)^B9 | C11: hab (+25 anios)
A12: Dotacion neta (Art. 43, clima calido) | B12: 140 | C12: L/hab.dia
A13: Perdidas tecnicas max. (Art. 44) | B13: 0.25 | C13: %
A14: Dotacion bruta | B14: =B12/(1-B13) | C14: L/hab.dia
A15: k1 (coef. max. diario) | B15: 1.3 | C15: Art. 47
A16: k2 (coef. max. horario) | B16: 1.6 | C16: Art. 47
A17: Caudal medio diario (Qmd) | B17: =B11*B14/86400 | C17: L/s
A18: Caudal maximo diario (QMD) | B18: =B17*B15 | C18: L/s
A19: Caudal maximo horario (QMH) | B19: =B18*B16 | C19: L/s
A20: Capacidad PTAP seleccionada | B20: 45 | C20: L/s

Sheet Supuestos
A1: SUPUESTOS DEL MODELO - PROYECTO PEPI (ACUEDUCTO DE TADO, CHOCO)
A2: Cifras en COP millones (salvo %). CAPEX anclado a inversion real (19.971 MM).
A3: Parametro | B3: Valor | C3: Unidad
A4: CAPEX total | B4: 19971 | C4: COP MM
A5: % Aporte publico (SGR/PDA/cooperacion) | B5: 0.8 | C5: %
A6: % Deuda (banca de desarrollo) | B6: 0.1 | C6: %
A7: % Equity (operador/municipio) | B7: 0.1 | C7: %
A8: Aporte publico | B8: =B4*B5 | C8: COP MM
A9: Deuda | B9: =B4*B6 | C9: COP MM
A10: Equity | B10: =B4*B7 | C10: COP MM
A11: Kd (costo deuda) | B11: 0.11 | C11: %
A12: Ke (costo equity) | B12: 0.14 | C12: %
A13: Tasa social de descuento (DNP) | B13: 0.09 | C13: %
A14: Tasa de impuestos | B14: 0.35 | C14: %
A15: Plazo de la deuda | B15: 10 | C15: anios
A16: Horizonte de evaluacion | B16: 25 | C16: anios
A17: Ingreso tarifa anio 1 | B17: 1500 | C17: COP MM
A18: Crecimiento ingresos | B18: 0.035 | C18: %
A19: OPEX anio 1 | B19: 1150 | C19: COP MM
A20: Crecimiento OPEX | B20: 0.035 | C20: %
A21: Beneficio social anio 1 | B21: 4150 | C21: COP MM
A22: Crecimiento beneficio social | B22: 0.035 | C22: %
A23: Depreciacion anual | B23: =B4/B16 | C23: COP MM
A24: Cuota anual deuda (frances) | B24: =B9*B11/(1-(1+B11)^(-B15)) | C24: COP MM
A25: WACC | B25: =B5*B13+B7*B12+B6*B11*(1-B14) | C25: %

Sheet Amortizacion Deuda
A1: TABLA DE AMORTIZACION DE LA DEUDA (Sistema Frances - cuota fija)
A2: Anio | B2: Saldo inicial | C2: Interes | D2: Abono capital | E2: Cuota | F2: Saldo final
A3: 1 | B3: =Supuestos!$B$9 | C3: =IF(A3<=Supuestos!$B$15,B3*Supuestos!$B$11,0) | D3: =E3-C3 | E3: =IF(A3<=Supuestos!$B$15,Supuestos!$B$24,0) | F3: =B3-D3
A4: 2 | B4: =F3 | C4: =IF(A4<=Supuestos!$B$15,B4*Supuestos!$B$11,0) | D4: =E4-C4 | E4: =IF(A4<=Supuestos!$B$15,Supuestos!$B$24,0) | F4: =B4-D4
A5: 3 | B5: =F4 | C5: =IF(A5<=Supuestos!$B$15,B5*Supuestos!$B$11,0) | D5: =E5-C5 | E5: =IF(A5<=Supuestos!$B$15,Supuestos!$B$24,0) | F5: =B5-D5
A6: 4 | B6: =F5 | C6: =IF(A6<=Supuestos!$B$15,B6*Supuestos!$B$11,0) | D6: =E6-C6 | E6: =IF(A6<=Supuestos!$B$15,Supuestos!$B$24,0) | F6: =B6-D6
A7: 5 | B7: =F6 | C7: =IF(A7<=Supuestos!$B$15,B7*Supuestos!$B$11,0) | D7: =E7-C7 | E7: =IF(A7<=Supuestos!$B$15,Supuestos!$B$24,0) | F7: =B7-D7
A8: 6 | B8: =F7 | C8: =IF(A8<=Supuestos!$B$15,B8*Supuestos!$B$11,0) | D8: =E8-C8 | E8: =IF(A8<=Supuestos!$B$15,Supuestos!$B$24,0) | F8: =B8-D8
A9: 7 | B9: =F8 | C9: =IF(A9<=Supuestos!$B$15,B9*Supuestos!$B$11,0) | D9: =E9-C9 | E9: =IF(A9<=Supuestos!$B$15,Supuestos!$B$24,0) | F9: =B9-D9
A10: 8 | B10: =F9 | C10: =IF(A10<=Supuestos!$B$15,B10*Supuestos!$B$11,0) | D10: =E10-C10 | E10: =IF(A10<=Supuestos!$B$15,Supuestos!$B$24,0) | F10: =B10-D10
A11: 9 | B11: =F10 | C11: =IF(A11<=Supuestos!$B$15,B11*Supuestos!$B$11,0) | D11: =E11-C11 | E11: =IF(A11<=Supuestos!$B$15,Supuestos!$B$24,0) | F11: =B11-D11
A12: 10 | B12: =F11 | C12: =IF(A12<=Supuestos!$B$15,B12*Supuestos!$B$11,0) | D12: =E12-C12 | E12: =IF(A12<=Supuestos!$B$15,Supuestos!$B$24,0) | F12: =B12-D12
A13: 11 | B13: =F12 | C13: =IF(A13<=Supuestos!$B$15,B13*Supuestos!$B$11,0) | D13: =E13-C13 | E13: =IF(A13<=Supuestos!$B$15,Supuestos!$B$24,0) | F13: =B13-D13
A14: 12 | B14: =F13 | C14: =IF(A14<=Supuestos!$B$15,B14*Supuestos!$B$11,0) | D14: =E14-C14 | E14: =IF(A14<=Supuestos!$B$15,Supuestos!$B$24,0) | F14: =B14-D14
A15: 13 | B15: =F14 | C15: =IF(A15<=Supuestos!$B$15,B15*Supuestos!$B$11,0) | D15: =E15-C15 | E15: =IF(A15<=Supuestos!$B$15,Supuestos!$B$24,0) | F15: =B15-D15
... A27: 25 | B27: =F26 | C27: =IF(A27<=Supuestos!$B$15,B27*Supuestos!$B$11,0) | D27: =E27-C27 | E27: =IF(A27<=Supuestos!$B$15,Supuestos!$B$24,0) | F27: =B27-D27

Sheet Flujos de Caja
A1: FLUJOS DE CAJA - PROYECTO, INVERSIONISTA, BANCO Y SOCIAL (COP MM)
A2: Anio | B2: Ingresos | C2: OPEX | D2: EBITDA | E2: Deprec. | F2: EBIT | G2: Intereses | H2: FC Proyecto | I2: Util. neta | J2: FC Inversionista | K2: FC Banco | L2: Benef. social | M2: FC Social
A3: 0 | H3: =-Supuestos!$B$4 | J3: =-Supuestos!$B$10 | K3: =Supuestos!$B$9 | M3: =-Supuestos!$B$4
A4: 1 | B4: =Supuestos!$B$17*(1+Supuestos!$B$18)^(A4-1) | C4: =Supuestos!$B$19*(1+Supuestos!$B$20)^(A4-1) | D4: =B4-C4 | E4: =Supuestos!$B$23 | F4: =D4-E4 | G4: ='Amortizacion Deuda'!C3 | H4: =D4-MAX(F4,0)*Supuestos!$B$14 | I4: =(F4-G4)-MAX(F4-G4,0)*Supuestos!$B$14 | J4: =I4+E4-'Amortizacion Deuda'!D3 | K4: =-'Amortizacion Deuda'!E3 | L4: =Supuestos!$B$21*(1+Supuestos!$B$22)^(A4-1) | M4: =L4-C4
A5: 2 | B5: =Supuestos!$B$17*(1+Supuestos!$B$18)^(A5-1) | C5: =Supuestos!$B$19*(1+Supuestos!$B$20)^(A5-1) | D5: =B5-C5 | E5: =Supuestos!$B$23 | F5: =D5-E5 | G5: ='Amortizacion Deuda'!C4 | H5: =D5-MAX(F5,0)*Supuestos!$B$14 | I5: =(F5-G5)-MAX(F5-G5,0)*Supuestos!$B$14 | J5: =I5+E5-'Amortizacion Deuda'!D4 | K5: =-'Amortizacion Deuda'!E4 | L5: =Supuestos!$B$21*(1+Supuestos!$B$22)^(A5-1) | M5: =L5-C5
A6: 3 | B6: =Supuestos!$B$17*(1+Supuestos!$B$18)^(A6-1) | C6: =Supuestos!$B$19*(1+Supuestos!$B$20)^(A6-1) | D6: =B6-C6 | E6: =Supuestos!$B$23 | F6: =D6-E6 | G6: ='Amortizacion Deuda'!C5 | H6: =D6-MAX(F6,0)*Supuestos!$B$14 | I6: =(F6-G6)-MAX(F6-G6,0)*Supuestos!$B$14 | J6: =I6+E6-'Amortizacion Deuda'!D5 | K6: =-'Amortizacion Deuda'!E5 | L6: =Supuestos!$B$21*(1+Supuestos!$B$22)^(A6-1) | M6: =L6-C6
A7: 4 | B7: =Supuestos!$B$17*(1+Supuestos!$B$18)^(A7-1) | C7: =Supuestos!$B$19*(1+Supuestos!$B$20)^(A7-1) | D7: =B7-C7 | E7: =Supuestos!$B$23 | F7: =D7-E7 | G7: ='Amortizacion Deuda'!C6 | H7: =D7-MAX(F7,0)*Supuestos!$B$14 | I7: =(F7-G7)-MAX(F7-G7,0)*Supuestos!$B$14 | J7: =I7+E7-'Amortizacion Deuda'!D6 | K7: =-'Amortizacion Deuda'!E6 | L7: =Supuestos!$B$21*(1+Supuestos!$B$22)^(A7-1) | M7: =L7-C7
A8: 5 | B8: =Supuestos!$B$17*(1+Supuestos!$B$18)^(A8-1) | C8: =Supuestos!$B$19*(1+Supuestos!$B$20)^(A8-1) | D8: =B8-C8 | E8: =Supuestos!$B$23 | F8: =D8-E8 | G8: ='Amortizacion Deuda'!C7 | H8: =D8-MAX(F8,0)*Supuestos!$B$14 | I8: =(F8-G8)-MAX(F8-G8,0)*Supuestos!$B$14 | J8: =I8+E8-'Amortizacion Deuda'!D7 | K8: =-'Amortizacion Deuda'!E7 | L8: =Supuestos!$B$21*(1+Supuestos!$B$22)^(A8-1) | M8: =L8-C8
A9: 6 | B9: =Supuestos!$B$17*(1+Supuestos!$B$18)^(A9-1) | C9: =Supuestos!$B$19*(1+Supuestos!$B$20)^(A9-1) | D9: =B9-C9 | E9: =Supuestos!$B$23 | F9: =D9-E9 | G9: ='Amortizacion Deuda'!C8 | H9: =D9-MAX(F9,0)*Supuestos!$B$14 | I9: =(F9-G9)-MAX(F9-G9,0)*Supuestos!$B$14 | J9: =I9+E9-'Amortizacion Deuda'!D8 | K9: =-'Amortizacion Deuda'!E8 | L9: =Supuestos!$B$21*(1+Supuestos!$B$22)^(A9-1) | M9: =L9-C9
A10: 7 | B10: =Supuestos!$B$17*(1+Supuestos!$B$18)^(A10-1) | C10: =Supuestos!$B$19*(1+Supuestos!$B$20)^(A10-1) | D10: =B10-C10 | E10: =Supuestos!$B$23 | F10: =D10-E10 | G10: ='Amortizacion Deuda'!C9 | H10: =D10-MAX(F10,0)*Supuestos!$B$14 | I10: =(F10-G10)-MAX(F10-G10,0)*Supuestos!$B$14 | J10: =I10+E10-'Amortizacion Deuda'!D9 | K10: =-'Amortizacion Deuda'!E9 | L10: =Supuestos!$B$21*(1+Supuestos!$B$22)^(A10-1) | M10: =L10-C10
A11: 8 | B11: =Supuestos!$B$17*(1+Supuestos!$B$18)^(A11-1) | C11: =Supuestos!$B$19*(1+Supuestos!$B$20)^(A11-1) | D11: =B11-C11 | E11: =Supuestos!$B$23 | F11: =D11-E11 | G11: ='Amortizacion Deuda'!C10 | H11: =D11-MAX(F11,0)*Supuestos!$B$14 | I11: =(F11-G11)-MAX(F11-G11,0)*Supuestos!$B$14 | J11: =I11+E11-'Amortizacion Deuda'!D10 | K11: =-'Amortizacion Deuda'!E10 | L11: =Supuestos!$B$21*(1+Supuestos!$B$22)^(A11-1) | M11: =L11-C11
A12: 9 | B12: =Supuestos!$B$17*(1+Supuestos!$B$18)^(A12-1) | C12: =Supuestos!$B$19*(1+Supuestos!$B$20)^(A12-1) | D12: =B12-C12 | E12: =Supuestos!$B$23 | F12: =D12-E12 | G12: ='Amortizacion Deuda'!C11 | H12: =D12-MAX(F12,0)*Supuestos!$B$14 | I12: =(F12-G12)-MAX(F12-G12,0)*Supuestos!$B$14 | J12: =I12+E12-'Amortizacion Deuda'!D11 | K12: =-'Amortizacion Deuda'!E11 | L12: =Supuestos!$B$21*(1+Supuestos!$B$22)^(A12-1) | M12: =L12-C12
A13: 10 | B13: =Supuestos!$B$17*(1+Supuestos!$B$18)^(A13-1) | C13: =Supuestos!$B$19*(1+Supuestos!$B$20)^(A13-1) | D13: =B13-C13 | E13: =Supuestos!$B$23 | F13: =D13-E13 | G13: ='Amortizacion Deuda'!C12 | H13: =D13-MAX(F13,0)*Supuestos!$B$14 | I13: =(F13-G13)-MAX(F13-G13,0)*Supuestos!$B$14 | J13: =I13+E13-'Amortizacion Deuda'!D12 | K13: =-'Amortizacion Deuda'!E12 | L13: =Supuestos!$B$21*(1+Supuestos!$B$22)^(A13-1) | M13: =L13-C13
A14: 11 | B14: =Supuestos!$B$17*(1+Supuestos!$B$18)^(A14-1) | C14: =Supuestos!$B$19*(1+Supuestos!$B$20)^(A14-1) | D14: =B14-C14 | E14: =Supuestos!$B$23 | F14: =D14-E14 | G14: ='Amortizacion Deuda'!C13 | H14: =D14-MAX(F14,0)*Supuestos!$B$14 | I14: =(F14-G14)-MAX(F14-G14,0)*Supuestos!$B$14 | J14: =I14+E14-'Amortizacion Deuda'!D13 | K14: =-'Amortizacion Deuda'!E13 | L14: =Supuestos!$B$21*(1+Supuestos!$B$22)^(A14-1) | M14: =L14-C14
A15: 12 | B15: =Supuestos!$B$17*(1+Supuestos!$B$18)^(A15-1) | C15: =Supuestos!$B$19*(1+Supuestos!$B$20)^(A15-1) | D15: =B15-C15 | E15: =Supuestos!$B$23 | F15: =D15-E15 | G15: ='Amortizacion Deuda'!C14 | H15: =D15-MAX(F15,0)*Supuestos!$B$14 | I15: =(F15-G15)-MAX(F15-G15,0)*Supuestos!$B$14 | J15: =I15+E15-'Amortizacion Deuda'!D14 | K15: =-'Amortizacion Deuda'!E14 | L15: =Supuestos!$B$21*(1+Supuestos!$B$22)^(A15-1) | M15: =L15-C15
... A28: 25 | B28: =Supuestos!$B$17*(1+Supuestos!$B$18)^(A28-1) | C28: =Supuestos!$B$19*(1+Supuestos!$B$20)^(A28-1) | D28: =B28-C28 | E28: =Supuestos!$B$23 | F28: =D28-E28 | G28: ='Amortizacion Deuda'!C27 | H28: =D28-MAX(F28,0)*Supuestos!$B$14 | I28: =(F28-G28)-MAX(F28-G28,0)*Supuestos!$B$14 | J28: =I28+E28-'Amortizacion Deuda'!D27 | K28: =-'Amortizacion Deuda'!E27 | L28: =Supuestos!$B$21*(1+Supuestos!$B$22)^(A28-1) | M28: =L28-C28

Sheet Indicadores
A1: INDICADORES DE RENTABILIDAD Y EVALUACION SOCIAL
A2: Indicador | B2: Valor | C2: Criterio
A3: WACC | B3: =Supuestos!$B$25 | C3: Costo promedio de capital
A4: VPN Proyecto (@WACC) | B4: ='Flujos de Caja'!$H$3+NPV(Supuestos!$B$25,'Flujos de Caja'!$H$4:$H$28) | C4: Si >0 crea valor (solo tarifas)
A5: TIR Proyecto | B5: =IRR('Flujos de Caja'!$H$3:$H$28) | C5: Viable si > WACC
A6: VPN Inversionista (@Ke) | B6: ='Flujos de Caja'!$J$3+NPV(Supuestos!$B$12,'Flujos de Caja'!$J$4:$J$28) | C6: Si >0 atractivo
A7: TIR Inversionista | B7: =IRR('Flujos de Caja'!$J$3:$J$28) | C7: Viable si > Ke
A8: VPN Social (@tasa social 9%) | B8: ='Flujos de Caja'!$M$3+NPV(Supuestos!$B$13,'Flujos de Caja'!$M$4:$M$28) | C8: Si >0 socialmente rentable
A9: Relacion Beneficio/Costo | B9: =NPV(Supuestos!$B$13,'Flujos de Caja'!$L$4:$L$28)/(Supuestos!$B$4+NPV(Supuestos!$B$13,'Flujos de Caja'!$C$4:$C$28)) | C9: Viable si > 1

Sheet Riesgos
A1: MATRIZ DE RIESGOS (20) - Nivel = P x I [Bajo 1-6 / Medio 8-12 / Alto 15-25]
A2: # | B2: Riesgo | C2: Tipo | D2: P | E2: I | F2: PxI | G2: Nivel
A3: 1 | B3: Crecientes/turbiedad extrema del rio San Juan | C3: Ambiental | D3: 4 | E3: 5 | F3: =D3*E3 | G3: =IF(F3>=15,"Alto",IF(F3>=8,"Medio","Bajo"))
A4: 2 | B4: Contaminacion por mineria ilegal (mercurio) | C4: Ambiental | D4: 4 | E4: 5 | F4: =D4*E4 | G4: =IF(F4>=15,"Alto",IF(F4>=8,"Medio","Bajo"))
A5: 3 | B5: Inundaciones que danan captacion/redes | C5: Ambiental | D5: 4 | E5: 4 | F5: =D5*E5 | G5: =IF(F5>=15,"Alto",IF(F5>=8,"Medio","Bajo"))
A6: 4 | B6: Deforestacion de la cuenca | C6: Ambiental | D6: 3 | E6: 3 | F6: =D6*E6 | G6: =IF(F6>=15,"Alto",IF(F6>=8,"Medio","Bajo"))
A7: 5 | B7: Vertimientos de aguas residuales a la fuente | C7: Ambiental | D7: 3 | E7: 4 | F7: =D7*E7 | G7: =IF(F7>=15,"Alto",IF(F7>=8,"Medio","Bajo"))
A8: 6 | B8: Resistencia comunitaria a micromedicion/tarifa | C8: Social | D8: 3 | E8: 3 | F8: =D8*E8 | G8: =IF(F8>=15,"Alto",IF(F8>=8,"Medio","Bajo"))
A9: 7 | B9: Baja cultura de pago y cartera morosa | C9: Social | D9: 4 | E9: 3 | F9: =D9*E9 | G9: =IF(F9>=15,"Alto",IF(F9>=8,"Medio","Bajo"))
A10: 8 | B10: Presencia de grupos armados (extorsion/retrasos) | C10: Seguridad | D10: 4 | E10: 4 | F10: =D10*E10 | G10: =IF(F10>=15,"Alto",IF(F10>=8,"Medio","Bajo"))
A11: 9 | B11: Demora en desembolsos de cofinanciacion | C11: Institucional | D11: 4 | E11: 4 | F11: =D11*E11 | G11: =IF(F11>=15,"Alto",IF(F11>=8,"Medio","Bajo"))
A12: 10 | B12: Debilidad del operador municipal | C12: Institucional | D12: 3 | E12: 4 | F12: =D12*E12 | G12: =IF(F12>=15,"Alto",IF(F12>=8,"Medio","Bajo"))
A13: 11 | B13: Sobrecostos por inflacion de insumos/transporte | C13: Financiero | D13: 3 | E13: 3 | F13: =D13*E13 | G13: =IF(F13>=15,"Alto",IF(F13>=8,"Medio","Bajo"))
A14: 12 | B14: Tarifa insuficiente para cubrir OPEX | C14: Financiero | D14: 4 | E14: 3 | F14: =D14*E14 | G14: =IF(F14>=15,"Alto",IF(F14>=8,"Medio","Bajo"))
... A22: 20 | B22: Brote de EDA durante la transicion de obra | C22: Salud publica | D22: 2 | E22: 4 | F22: =D22*E22 | G22: =IF(F22>=15,"Alto",IF(F22>=8,"Medio","Bajo"))
A25: INTERVENCION DE 10 RIESGOS (5 ambientales) Y RECALIFICACION RESIDUAL
A26: # | B26: Riesgo | C26: Tipo | D26: Intervencion | E26: P res | F26: I res | G26: PxI res | H26: Nivel res
A27: 1 | B27: Turbiedad extrema del rio San Juan | C27: Ambiental | D27: Pretratamiento robusto + sedimentadores alta tasa + dosificacion automatica + tanque de regulacion | E27: 2 | F27: 4 | G27: =E27*F27 | H27: =IF(G27>=15,"Alto",IF(G27>=8,"Medio","Bajo"))
A28: 2 | B28: Contaminacion por mineria ilegal | C28: Ambiental | D28: Monitoreo de fuente + carbon activado + articulacion con CODECHOCO y control de mineria | E28: 3 | F28: 3 | G28: =E28*F28 | H28: =IF(G28>=15,"Alto",IF(G28>=8,"Medio","Bajo"))
A29: 3 | B29: Inundaciones que danan infraestructura | C29: Ambiental | D29: Captacion elevada/protegida + obras de proteccion de orillas + redes en cotas seguras | E29: 2 | F29: 4 | G29: =E29*F29 | H29: =IF(G29>=15,"Alto",IF(G29>=8,"Medio","Bajo"))
A30: 5 | B30: Vertimientos a la fuente | C30: Ambiental | D30: Optimizacion de alcantarillado + campanas + coordinacion municipal | E30: 2 | F30: 3 | G30: =E30*F30 | H30: =IF(G30>=15,"Alto",IF(G30>=8,"Medio","Bajo"))
A31: 4 | B31: Deforestacion de la cuenca | C31: Ambiental | D31: Pago por servicios ambientales + reforestacion de microcuenca con la comunidad | E31: 2 | F31: 2 | G31: =E31*F31 | H31: =IF(G31>=15,"Alto",IF(G31>=8,"Medio","Bajo"))
A32: 8 | B32: Grupos armados / inseguridad | C32: Seguridad | D32: Plan de seguridad de obra + articulacion con autoridades + contratacion local | E32: 2 | F32: 4 | G32: =E32*F32 | H32: =IF(G32>=15,"Alto",IF(G32>=8,"Medio","Bajo"))
A33: 9 | B33: Demora en desembolsos | C33: Institucional | D33: Convenio con desembolsos por hitos + anticipo + fiducia | E33: 2 | F33: 4 | G33: =E33*F33 | H33: =IF(G33>=15,"Alto",IF(G33>=8,"Medio","Bajo"))
A34: 7 | B34: Baja cultura de pago | C34: Social | D34: Subsidios focalizados + educacion + tarifa social + facturacion clara | E34: 2 | F34: 3 | G34: =E34*F34 | H34: =IF(G34>=15,"Alto",IF(G34>=8,"Medio","Bajo"))
A35: 12 | B35: Tarifa insuficiente | C35: Financiero | D35: Estudio tarifario CRA + subsidios cruzados + aporte SGP | E35: 2 | F35: 3 | G35: =E35*F35 | H35: =IF(G35>=15,"Alto",IF(G35>=8,"Medio","Bajo"))
A36: 15 | B36: Suministro electrico inestable | C36: Tecnico | D36: Planta electrica de respaldo + almacenamiento con autonomia | E36: 2 | F36: 3 | G36: =E36*F36 | H36: =IF(G36>=15,"Alto",IF(G36>=8,"Medio","Bajo"))
